{"type":"FeatureCollection","features":[{"type":"Feature","properties":{"GeoX":"8.28651545","GeoY":"46.80966278","sovereignt":"Switzerland","sov_a3":"CHE","pop_est":"7604467","gdp_md_est":"316700","fill":"RGB(84,0,0)","coefficient":"-1.06803582","intercept":"98.19978083"},"geometry":{"type":"Point","coordinates":[8.286515,46.809663]}},{"type":"Feature","properties":{"GeoX":"25.1385334","GeoY":"42.73942044","sovereignt":"Bulgaria","sov_a3":"BGR","pop_est":"7204687","gdp_md_est":"93750","fill":"RGB(97,0,0)","coefficient":"-1.22651441","intercept":"97.78722901"},"geometry":{"type":"Point","coordinates":[25.138533,42.73942]}},{"type":"Feature","properties":{"GeoX":"27.78641098","GeoY":"53.70603823","sovereignt":"Belarus","sov_a3":"BLR","pop_est":"9648533","gdp_md_est":"114100","fill":"RGB(90,0,0)","coefficient":"-1.14379084","intercept":"95.83762775"},"geometry":{"type":"Point","coordinates":[27.786411,53.706038]}},{"type":"Feature","properties":{"GeoX":"19.96759001","GeoY":"41.24789642","sovereignt":"Albania","sov_a3":"ALB","pop_est":"3639453","gdp_md_est":"21810","fill":"RGB(90,0,0)","coefficient":"-1.14667225","intercept":"96.84328008"},"geometry":{"type":"Point","coordinates":[19.96759,41.247896]}},{"type":"Feature","properties":{"GeoX":"14.95314982","GeoY":"47.91918114","sovereignt":"Austria","sov_a3":"AUT","pop_est":"8210281","gdp_md_est":"329500","fill":"RGB(21,0,0)","coefficient":"-0.27087215","intercept":"84.63423532"},"geometry":{"type":"Point","coordinates":[14.95315,47.919181]}},{"type":"Feature","properties":{"GeoX":"18.11515989","GeoY":"43.8530957","sovereignt":"Bosnia and Herzegovina","sov_a3":"BIH","pop_est":"4613414","gdp_md_est":"29700","fill":"RGB(28,0,0)","coefficient":"-0.35258729","intercept":"80.77164558"},"geometry":{"type":"Point","coordinates":[18.11516,43.853096]}},{"type":"Feature","properties":{"GeoX":"4.737356636","GeoY":"50.57967697","sovereignt":"Belgium","sov_a3":"BEL","pop_est":"10414336","gdp_md_est":"389300","fill":"RGB(51,0,0)","coefficient":"-0.64791716","intercept":"89.5577034"},"geometry":{"type":"Point","coordinates":[4.737357,50.579677]}},{"type":"Feature","properties":{"GeoX":"15.53816659","GeoY":"49.75826772","sovereignt":"Czech Republic","sov_a3":"CZE","pop_est":"10211904","gdp_md_est":"265200","fill":"RGB(69,0,0)","coefficient":"-0.88132614","intercept":"94.01999901"},"geometry":{"type":"Point","coordinates":[15.538167,49.758268]}},{"type":"Feature","properties":{"GeoX":"10.43235134","GeoY":"51.43122745","sovereignt":"Germany","sov_a3":"DEU","pop_est":"82329758","gdp_md_est":"2918000","fill":"RGB(148,0,0)","coefficient":"-1.88100826","intercept":"100.742741"},"geometry":{"type":"Point","coordinates":[10.432351,51.431227]}},{"type":"Feature","properties":{"GeoX":"9.460776729","GeoY":"56.32431343","sovereignt":"Denmark","sov_a3":"DN1","pop_est":"5500510","gdp_md_est":"203600","fill":"RGB(185,0,0)","coefficient":"-2.34616341","intercept":"93.91513084"},"geometry":{"type":"Point","coordinates":[9.460777,56.324313]}},{"type":"Feature","properties":{"GeoX":"-3.51996786","GeoY":"39.91791272","sovereignt":"Spain","sov_a3":"ESP","pop_est":"40525002","gdp_md_est":"1403000","fill":"RGB(276,0,0)","coefficient":"-3.50694079","intercept":"103.3276602"},"geometry":{"type":"Point","coordinates":[-3.519968,39.917913]}},{"type":"Feature","properties":{"GeoX":"27.37328983","GeoY":"65.03004945","sovereignt":"Finland","sov_a3":"FI1","pop_est":"5250275","gdp_md_est":"193500","fill":"RGB(99,0,0)","coefficient":"-1.2534266","intercept":"98.43871641"},"geometry":{"type":"Point","coordinates":[27.37329,65.030049]}},{"type":"Feature","properties":{"GeoX":"-1.753312356","GeoY":"54.22468799","sovereignt":"United Kingdom","sov_a3":"GB1","pop_est":"62262000","gdp_md_est":"1977704","fill":"RGB(102,0,0)","coefficient":"-1.29614453","intercept":"97.87034695"},"geometry":{"type":"Point","coordinates":[-1.753312,54.224688]}},{"type":"Feature","properties":{"GeoX":"21.80633166","GeoY":"39.08045676","sovereignt":"Greece","sov_a3":"GRC","pop_est":"10737428","gdp_md_est":"343000","fill":"RGB(71,0,0)","coefficient":"-0.90370323","intercept":"96.75536617"},"geometry":{"type":"Point","coordinates":[21.806332,39.080457]}},{"type":"Feature","properties":{"GeoX":"25.56175754","GeoY":"58.49808221","sovereignt":"Estonia","sov_a3":"EST","pop_est":"1299371","gdp_md_est":"27410","fill":"RGB(88,0,0)","coefficient":"-1.12012706","intercept":"94.32710571"},"geometry":{"type":"Point","coordinates":[25.561758,58.498082]}},{"type":"Feature","properties":{"GeoX":"2.099228161","GeoY":"46.89507007","sovereignt":"France","sov_a3":"FR1","pop_est":"64057792","gdp_md_est":"2128000","fill":"RGB(172,0,0)","coefficient":"-2.185274","intercept":"97.82560963"},"geometry":{"type":"Point","coordinates":[2.099228,46.89507]}},{"type":"Feature","properties":{"GeoX":"15.58355931","GeoY":"44.54481364","sovereignt":"Croatia","sov_a3":"HRV","pop_est":"4489409","gdp_md_est":"82390","fill":"RGB(253,0,0)","coefficient":"-3.21638545","intercept":"110.5800798"},"geometry":{"type":"Point","coordinates":[15.583559,44.544814]}},{"type":"Feature","properties":{"GeoX":"-7.80669901","GeoY":"53.51036481","sovereignt":"Ireland","sov_a3":"IRL","pop_est":"4203200","gdp_md_est":"188400","fill":"RGB(120,0,0)","coefficient":"-1.51830571","intercept":"110.1726886"},"geometry":{"type":"Point","coordinates":[-7.806699,53.510365]}},{"type":"Feature","properties":{"GeoX":"19.10324825","GeoY":"47.24520401","sovereignt":"Hungary","sov_a3":"HUN","pop_est":"9905596","gdp_md_est":"196600","fill":"RGB(58,0,0)","coefficient":"-0.73917844","intercept":"84.77961017"},"geometry":{"type":"Point","coordinates":[19.103248,47.245204]}},{"type":"Feature","properties":{"GeoX":"12.63118349","GeoY":"42.55821652","sovereignt":"Italy","sov_a3":"ITA","pop_est":"58126212","gdp_md_est":"1823000","fill":"RGB(59,0,0)","coefficient":"-0.75233418","intercept":"83.69603014"},"geometry":{"type":"Point","coordinates":[12.631183,42.558217]}},{"type":"Feature","properties":{"GeoX":"-18.45789129","GeoY":"64.98804996","sovereignt":"Iceland","sov_a3":"ISL","pop_est":"306694","gdp_md_est":"12710","fill":"RGB(189,0,0)","coefficient":"-2.39314335","intercept":"109.1762306"},"geometry":{"type":"Point","coordinates":[-18.457891,64.98805]}},{"type":"Feature","properties":{"GeoX":"20.91366238","GeoY":"42.51392448","sovereignt":"Kosovo","sov_a3":"KOS","pop_est":"1804838","gdp_md_est":"5352","fill":"RGB(113,0,0)","coefficient":"-1.43040879","intercept":"102.7020176"},"geometry":{"type":"Point","coordinates":[20.913662,42.513924]}},{"type":"Feature","properties":{"GeoX":"24.12780131","GeoY":"55.09123614","sovereignt":"Lithuania","sov_a3":"LTU","pop_est":"3555179","gdp_md_est":"63330","fill":"RGB(74,0,0)","coefficient":"-0.93775827","intercept":"87.1012411"},"geometry":{"type":"Point","coordinates":[24.127801,55.091236]}},{"type":"Feature","properties":{"GeoX":"5.964412511","GeoY":"49.71585463","sovereignt":"Luxembourg","sov_a3":"LUX","pop_est":"491775","gdp_md_est":"39370","fill":"RGB(27,0,0)","coefficient":"-0.34465727","intercept":"83.8955072"},"geometry":{"type":"Point","coordinates":[5.964413,49.715855]}},{"type":"Feature","properties":{"GeoX":"19.07626746","GeoY":"51.88441746","sovereignt":"Poland","sov_a3":"POL","pop_est":"38482919","gdp_md_est":"667900","fill":"RGB(84,0,0)","coefficient":"-1.06245021","intercept":"95.17083971"},"geometry":{"type":"Point","coordinates":[19.076267,51.884417]}},{"type":"Feature","properties":{"GeoX":"24.50442327","GeoY":"56.89505545","sovereignt":"Latvia","sov_a3":"LVA","pop_est":"2231503","gdp_md_est":"38860","fill":"RGB(235,0,0)","coefficient":"-2.98382672","intercept":"105.0059258"},"geometry":{"type":"Point","coordinates":[24.504423,56.895055]}},{"type":"Feature","properties":{"GeoX":"28.64903798","GeoY":"47.13761452","sovereignt":"Moldova","sov_a3":"MDA","pop_est":"4320748","gdp_md_est":"10670","fill":"RGB(49,0,0)","coefficient":"-0.62553545","intercept":"91.44143236"},"geometry":{"type":"Point","coordinates":[28.649038,47.137615]}},{"type":"Feature","properties":{"GeoX":"19.39621572","GeoY":"42.75049738","sovereignt":"Montenegro","sov_a3":"MNE","pop_est":"672180","gdp_md_est":"6816","fill":"RGB(209,0,0)","coefficient":"-2.64732211","intercept":"104.5292335"},"geometry":{"type":"Point","coordinates":[19.396216,42.750497]}},{"type":"Feature","properties":{"GeoX":"5.398112884","GeoY":"52.04023413","sovereignt":"Netherlands","sov_a3":"NL1","pop_est":"16715999","gdp_md_est":"672000","fill":"RGB(129,0,0)","coefficient":"-1.63774788","intercept":"93.35627937"},"geometry":{"type":"Point","coordinates":[5.398113,52.040234]}},{"type":"Feature","properties":{"GeoX":"21.72033934","GeoY":"41.6811007","sovereignt":"Macedonia","sov_a3":"MKD","pop_est":"2066718","gdp_md_est":"18780","fill":"RGB(95,0,0)","coefficient":"-1.20700097","intercept":"98.76254056"},"geometry":{"type":"Point","coordinates":[21.720339,41.681101]}},{"type":"Feature","properties":{"GeoX":"21.01347523","GeoY":"44.13669595","sovereignt":"Republic of Serbia","sov_a3":"SRB","pop_est":"7379339","gdp_md_est":"80340","fill":"RGB(35,0,0)","coefficient":"-0.44600301","intercept":"86.97068149"},"geometry":{"type":"Point","coordinates":[21.013475,44.136696]}},{"type":"Feature","properties":{"GeoX":"22.68248646","GeoY":"79.95814208","sovereignt":"Norway","sov_a3":"NOR","pop_est":"4676305","gdp_md_est":"276400","fill":"RGB(69,0,0)","coefficient":"-0.88120443","intercept":"93.38222583"},"geometry":{"type":"Point","coordinates":[22.682486,79.958142]}},{"type":"Feature","properties":{"GeoX":"-8.367926306","GeoY":"39.51081861","sovereignt":"Portugal","sov_a3":"PRT","pop_est":"10707924","gdp_md_est":"208627","fill":"RGB(122,0,0)","coefficient":"-1.55169971","intercept":"107.4864895"},"geometry":{"type":"Point","coordinates":[-8.367926,39.510819]}},{"type":"Feature","properties":{"GeoX":"88.59732851","GeoY":"59.40586917","sovereignt":"Russia","sov_a3":"RUS","pop_est":"140041247","gdp_md_est":"2266000","fill":"RGB(167,0,0)","coefficient":"-2.12353296","intercept":"104.9238659"},"geometry":{"type":"Point","coordinates":[88.597329,59.405869]}},{"type":"Feature","properties":{"GeoX":"24.2116923","GeoY":"46.03602716","sovereignt":"Romania","sov_a3":"ROU","pop_est":"22215421","gdp_md_est":"271400","fill":"RGB(177,0,0)","coefficient":"-2.24906109","intercept":"96.73196409"},"geometry":{"type":"Point","coordinates":[24.211692,46.036027]}},{"type":"Feature","properties":{"GeoX":"14.73228097","GeoY":"46.12744286","sovereignt":"Slovenia","sov_a3":"SVN","pop_est":"2005692","gdp_md_est":"59340","fill":"RGB(120,0,0)","coefficient":"-1.52709586","intercept":"100.413691"},"geometry":{"type":"Point","coordinates":[14.732281,46.127443]}},{"type":"Feature","properties":{"GeoX":"33.89278106","GeoY":"48.30030764","sovereignt":"Ukraine","sov_a3":"UKR","pop_est":"45700395","gdp_md_est":"339800","fill":"RGB(25,0,0)","coefficient":"-0.31145958","intercept":"76.99482278"},"geometry":{"type":"Point","coordinates":[33.892781,48.300308]}},{"type":"Feature","properties":{"GeoX":"19.63011378","GeoY":"48.71193654","sovereignt":"Slovakia","sov_a3":"SVK","pop_est":"5463046","gdp_md_est":"119500","fill":"RGB(119,0,0)","coefficient":"-1.50588722","intercept":"97.76657141"},"geometry":{"type":"Point","coordinates":[19.630114,48.711937]}},{"type":"Feature","properties":{"GeoX":"14.78624339","GeoY":"62.27488088","sovereignt":"Sweden","sov_a3":"SWE","pop_est":"9059651","gdp_md_est":"344300"},"geometry":{"type":"Point","coordinates":[14.786243,62.274881]}}]}
